bgdiscovery/__init__.py
bgdiscovery/_version.py
bgdiscovery/bgdiscovery.py
bgdiscovery-0.9.40.dist-info/METADATA
bgdiscovery-0.9.40.dist-info/WHEEL
bgdiscovery-0.9.40.dist-info/entry_points.txt
bgdiscovery-0.9.40.dist-info/top_level.txt
bgdiscovery-0.9.40.dist-info/RECORD
