Metadata-Version: 2.1
Name: bgdiscovery
Version: 0.9.40
Summary: biGENIUS Discovery App.
Home-page: https://www.bigenius.info/
Author: biGENIUS AG
Author-email: gergely.szecsenyi@bigenius.info
Classifier: Programming Language :: Python :: 3.9
Requires-Dist: pyodbc (==4.0.35)
Requires-Dist: pyyaml
Requires-Dist: art (==5.8)
Requires-Dist: coloredlogs
Requires-Dist: colorama
Requires-Dist: pydantic (<2.0.0)
Requires-Dist: acryl-datahub (==0.12.0.5)
